pypki3/README.md
pypki3/__init__.py
pypki3/config.py
pypki3/exceptions.py
pypki3/utils.py
pypki3-2025.183.1233.dist-info/LICENSE
pypki3-2025.183.1233.dist-info/METADATA
pypki3-2025.183.1233.dist-info/WHEEL
pypki3-2025.183.1233.dist-info/RECORD
