Metadata-Version: 2.3
Name: pypki3
Version: 2025.183.1233
Summary: More user-friendly way to access PKI-enabled services.
License: MIT
Author: Bill Allen
Author-email: billallen256@gmail.com
Requires-Python: >=3.6
Classifier: License :: OSI Approved :: MIT License
Classifier: Programming Language :: Python :: 3
Classifier: Programming Language :: Python :: 3.6
Classifier: Programming Language :: Python :: 3.7
Classifier: Programming Language :: Python :: 3.8
Classifier: Programming Language :: Python :: 3.9
Classifier: Programming Language :: Python :: 3.10
Classifier: Programming Language :: Python :: 3.11
Classifier: Programming Language :: Python :: 3.12
Classifier: Programming Language :: Python :: 3.13
Requires-Dist: cryptography
Requires-Dist: pem
Requires-Dist: temppath
Project-URL: Homepage, http://github.com/nbgallery/pypki3
